DimensionalityReduction/__init__.py
DimensionalityReduction-1.1.4.dist-info/LICENSE.txt
DimensionalityReduction-1.1.4.dist-info/METADATA
DimensionalityReduction-1.1.4.dist-info/WHEEL
DimensionalityReduction-1.1.4.dist-info/top_level.txt
DimensionalityReduction-1.1.4.dist-info/RECORD
